{
  "base": {
    "packages": [
      {
        "name": "st4sd-lammps-with-restart",
        "source": {
          "git": {
            "location": {
              "url": "https://github.com/ashkurti/st4sd-lammps-with-restart",
              "commit": "68ec8bf3d424725e7bbc293c1b7303b915c69f21"
            }
          }
        }
      }
    ]
  },
  "metadata": {
    "package": {
      "name": "st4sd-lammps-with-restart",
      "tags": [],
      "license": "",
      "maintainer": "",
      "description": "",
      "keywords": []
    }
  },
  "parameterisation": {
    "presets": {
      "platform": "default",
      "variables": [
        {
          "name": "input.confin.data",
          "value": "input/confin.data"
        },
        {
          "name": "pvc-output-dir",
          "value": "/tmp/st4sd-volumes/pvc-md-simulation-inputs-pvc-rwx/lammps_with_restart_data"
        },
        {
          "name": "path-env",
          "value": "/usr/local/lammps/bin:/usr/local/lammps/sm80/bin:/usr/local/openmpi/bin:/usr/local/ucx/bin:/usr/local/nvidia/bin:/usr/local/cuda/bin:/usr/local/sbin:/usr/local/bin:/usr/sbin:/usr/bin:/sbin:/bin"
        },
        {
          "name": "lammps-cpus",
          "value": "1"
        },
        {
          "name": "lammps-gpus",
          "value": "1"
        },
        {
          "name": "input.file.in",
          "value": "input/file.in"
        },
        {
          "name": "ld-library-path",
          "value": "/usr/local/lammps/sm80/lib:/usr/local/cuda/lib:/usr/local/cuda/lib64:/usr/local/fftw/lib"
        }
      ]
    },
    "executionOptions": {
      "variables": [
        {
          "name": "restart-iterations",
          "value": "2"
        }
      ]
    }
  }
}
